nutellaAgent/__init__.py
nutellaAgent/nu_hpo.py
nutellaAgent/nu_hpo_utils.py
nutellaAgent/nu_importance.py
nutellaAgent/nu_requests.py
nutellaAgent/nu_sdk.py
nutellaAgent/nu_tpe.py
nutellaAgent/nutella_hpo/__init__.py
nutellaAgent/nutella_hpo/nu_hpo.py
nutellaAgent/nutella_hpo/nu_hpo_utils.py
nutellaAgent/nutella_hpo/nu_tpe.py
nutellaAgent-0.2.1.dist-info/LICENSE
nutellaAgent-0.2.1.dist-info/METADATA
nutellaAgent-0.2.1.dist-info/WHEEL
nutellaAgent-0.2.1.dist-info/top_level.txt
nutellaAgent-0.2.1.dist-info/RECORD
