Metadata-Version: 2.1
Name: nutellaAgent
Version: 0.2.1
Summary: for nutella service
Home-page: UNKNOWN
Author: songpie
Author-email: songmi.ohh@gmail.com
License: MIT
Keywords: nutellaAgent
Platform: UNKNOWN
Classifier: Programming Language :: Python :: 3
Classifier: Programming Language :: Python :: 3.8
Requires-Python: >=3.7
Requires-Dist: aiohttp
Requires-Dist: hyperopt
Requires-Dist: fanova
